mercadolibre/__init__.py
mercadolibre/client.py
mercadolibre/decorators.py
mercadolibre/error.py
mercadolibre/exceptions.py
mercadolibre/localhost.crt
mercadolibre/localhost.key
mercadolibre/response.py
mercadolibre/utils.py
mercadolibre_wrapper-0.2.dist-info/METADATA
mercadolibre_wrapper-0.2.dist-info/WHEEL
mercadolibre_wrapper-0.2.dist-info/top_level.txt
mercadolibre_wrapper-0.2.dist-info/RECORD
