Metadata-Version: 2.1
Name: mercadolibre-wrapper
Version: 0.2
Summary: UNKNOWN
Home-page: https://github.com/ezecavallo/mercadoLibre_wrapper
Author: UNKNOWN
Author-email: UNKNOWN
License: MIT
Platform: UNKNOWN
Requires-Dist: requests
